{
  "games": [
    {
      "GAME_DATE": "Apr 13, 2025",
      "MATCHUP": "CHI @ PHI",
      "MIN": 22.0,
      "FGM": 2,
      "FGA": 9,
      "FG3M": 1,
      "FG3A": 7,
      "FTM": 0,
      "FTA": 0,
      "OREB": 1,
      "DREB": 3,
      "REB": 4,
      "AST": 2,
      "STL": 0,
      "BLK": 0,
      "TOV": 0,
      "PF": 2,
      "PTS": 5,
      "PLUS_MINUS": 26
    },
    {
      "GAME_DATE": "Apr 11, 2025",
      "MATCHUP": "CHI vs. WAS",
      "MIN": 13.0,
      "FGM": 3,
      "FGA": 10,
      "FG3M": 2,
      "FG3A": 8,
      "FTM": 0,
      "FTA": 0,
      "OREB": 0,
      "DREB": 3,
      "REB": 3,
      "AST": 1,
      "STL": 0,
      "BLK": 0,
      "TOV": 0,
      "PF": 0,
      "PTS": 8,
      "PLUS_MINUS": 15
    },
    {
      "GAME_DATE": "Apr 08, 2025",
      "MATCHUP": "CHI @ CLE",
      "MIN": 34.0,
      "FGM": 4,
      "FGA": 15,
      "FG3M": 2,
      "FG3A": 9,
      "FTM": 0,
      "FTA": 0,
      "OREB": 0,
      "DREB": 1,
      "REB": 1,
      "AST": 3,
      "STL": 4,
      "BLK": 0,
      "TOV": 1,
      "PF": 1,
      "PTS": 10,
      "PLUS_MINUS": -18
    },
    {
      "GAME_DATE": "Apr 06, 2025",
      "MATCHUP": "CHI @ CHA",
      "MIN": 2.0,
      "FGM": 0,
      "FGA": 0,
      "FG3M": 0,
      "FG3A": 0,
      "FTM": 0,
      "FTA": 0,
      "OREB": 0,
      "DREB": 0,
      "REB": 0,
      "AST": 0,
      "STL": 0,
      "BLK": 0,
      "TOV": 1,
      "PF": 0,
      "PTS": 0,
      "PLUS_MINUS": -11
    },
    {
      "GAME_DATE": "Mar 31, 2025",
      "MATCHUP": "CHI @ OKC",
      "MIN": 18.0,
      "FGM": 6,
      "FGA": 14,
      "FG3M": 5,
      "FG3A": 11,
      "FTM": 0,
      "FTA": 0,
      "OREB": 1,
      "DREB": 1,
      "REB": 2,
      "AST": 3,
      "STL": 0,
      "BLK": 0,
      "TOV": 0,
      "PF": 1,
      "PTS": 17,
      "PLUS_MINUS": 3
    },
    {
      "GAME_DATE": "Mar 22, 2025",
      "MATCHUP": "CHI @ LAL",
      "MIN": 4.0,
      "FGM": 1,
      "FGA": 1,
      "FG3M": 0,
      "FG3A": 0,
      "FTM": 0,
      "FTA": 0,
      "OREB": 0,
      "DREB": 1,
      "REB": 1,
      "AST": 0,
      "STL": 0,
      "BLK": 1,
      "TOV": 0,
      "PF": 0,
      "PTS": 2,
      "PLUS_MINUS": 4
    },
    {
      "GAME_DATE": "Mar 10, 2025",
      "MATCHUP": "CHI vs. IND",
      "MIN": 3.0,
      "FGM": 2,
      "FGA": 3,
      "FG3M": 1,
      "FG3A": 2,
      "FTM": 0,
      "FTA": 0,
      "OREB": 0,
      "DREB": 0,
      "REB": 0,
      "AST": 1,
      "STL": 0,
      "BLK": 0,
      "TOV": 0,
      "PF": 0,
      "PTS": 5,
      "PLUS_MINUS": -6
    },
    {
      "GAME_DATE": "Mar 04, 2025",
      "MATCHUP": "CHI vs. CLE",
      "MIN": 16.0,
      "FGM": 1,
      "FGA": 5,
      "FG3M": 1,
      "FG3A": 5,
      "FTM": 0,
      "FTA": 0,
      "OREB": 0,
      "DREB": 2,
      "REB": 2,
      "AST": 3,
      "STL": 1,
      "BLK": 1,
      "TOV": 0,
      "PF": 1,
      "PTS": 3,
      "PLUS_MINUS": 1
    },
    {
      "GAME_DATE": "Mar 02, 2025",
      "MATCHUP": "CHI @ IND",
      "MIN": 14.0,
      "FGM": 1,
      "FGA": 3,
      "FG3M": 0,
      "FG3A": 1,
      "FTM": 0,
      "FTA": 0,
      "OREB": 0,
      "DREB": 1,
      "REB": 1,
      "AST": 1,
      "STL": 1,
      "BLK": 0,
      "TOV": 0,
      "PF": 2,
      "PTS": 2,
      "PLUS_MINUS": -10
    },
    {
      "GAME_DATE": "Feb 24, 2025",
      "MATCHUP": "CHI @ PHI",
      "MIN": 7.0,
      "FGM": 2,
      "FGA": 4,
      "FG3M": 2,
      "FG3A": 4,
      "FTM": 2,
      "FTA": 2,
      "OREB": 0,
      "DREB": 0,
      "REB": 0,
      "AST": 0,
      "STL": 0,
      "BLK": 0,
      "TOV": 0,
      "PF": 0,
      "PTS": 8,
      "PLUS_MINUS": -14
    },
    {
      "GAME_DATE": "Feb 11, 2025",
      "MATCHUP": "CHI vs. DET",
      "MIN": 11.0,
      "FGM": 1,
      "FGA": 5,
      "FG3M": 1,
      "FG3A": 3,
      "FTM": 0,
      "FTA": 0,
      "OREB": 0,
      "DREB": 2,
      "REB": 2,
      "AST": 4,
      "STL": 0,
      "BLK": 0,
      "TOV": 1,
      "PF": 0,
      "PTS": 3,
      "PLUS_MINUS": 4
    },
    {
      "GAME_DATE": "Feb 08, 2025",
      "MATCHUP": "CHI vs. GSW",
      "MIN": 4.0,
      "FGM": 0,
      "FGA": 3,
      "FG3M": 0,
      "FG3A": 3,
      "FTM": 0,
      "FTA": 0,
      "OREB": 0,
      "DREB": 1,
      "REB": 1,
      "AST": 1,
      "STL": 0,
      "BLK": 0,
      "TOV": 0,
      "PF": 0,
      "PTS": 0,
      "PLUS_MINUS": 4
    },
    {
      "GAME_DATE": "Feb 05, 2025",
      "MATCHUP": "CHI @ MIN",
      "MIN": 23.0,
      "FGM": 4,
      "FGA": 7,
      "FG3M": 2,
      "FG3A": 4,
      "FTM": 0,
      "FTA": 0,
      "OREB": 0,
      "DREB": 2,
      "REB": 2,
      "AST": 6,
      "STL": 1,
      "BLK": 0,
      "TOV": 1,
      "PF": 1,
      "PTS": 10,
      "PLUS_MINUS": 4
    },
    {
      "GAME_DATE": "Feb 04, 2025",
      "MATCHUP": "CHI vs. MIA",
      "MIN": 6.0,
      "FGM": 1,
      "FGA": 3,
      "FG3M": 0,
      "FG3A": 2,
      "FTM": 0,
      "FTA": 0,
      "OREB": 0,
      "DREB": 0,
      "REB": 0,
      "AST": 0,
      "STL": 0,
      "BLK": 0,
      "TOV": 0,
      "PF": 0,
      "PTS": 2,
      "PLUS_MINUS": -5
    },
    {
      "GAME_DATE": "Feb 02, 2025",
      "MATCHUP": "CHI @ DET",
      "MIN": 12.0,
      "FGM": 2,
      "FGA": 6,
      "FG3M": 1,
      "FG3A": 5,
      "FTM": 0,
      "FTA": 0,
      "OREB": 0,
      "DREB": 4,
      "REB": 4,
      "AST": 0,
      "STL": 1,
      "BLK": 0,
      "TOV": 0,
      "PF": 1,
      "PTS": 5,
      "PLUS_MINUS": 1
    },
    {
      "GAME_DATE": "Jan 29, 2025",
      "MATCHUP": "CHI @ BOS",
      "MIN": 4.0,
      "FGM": 1,
      "FGA": 3,
      "FG3M": 1,
      "FG3A": 3,
      "FTM": 0,
      "FTA": 0,
      "OREB": 0,
      "DREB": 0,
      "REB": 0,
      "AST": 1,
      "STL": 0,
      "BLK": 0,
      "TOV": 0,
      "PF": 0,
      "PTS": 3,
      "PLUS_MINUS": -4
    },
    {
      "GAME_DATE": "Jan 23, 2025",
      "MATCHUP": "CHI @ GSW",
      "MIN": 6.0,
      "FGM": 3,
      "FGA": 7,
      "FG3M": 3,
      "FG3A": 6,
      "FTM": 0,
      "FTA": 0,
      "OREB": 0,
      "DREB": 1,
      "REB": 1,
      "AST": 0,
      "STL": 0,
      "BLK": 0,
      "TOV": 0,
      "PF": 1,
      "PTS": 9,
      "PLUS_MINUS": 1
    },
    {
      "GAME_DATE": "Jan 15, 2025",
      "MATCHUP": "CHI vs. ATL",
      "MIN": 4.0,
      "FGM": 0,
      "FGA": 2,
      "FG3M": 0,
      "FG3A": 1,
      "FTM": 0,
      "FTA": 0,
      "OREB": 0,
      "DREB": 0,
      "REB": 0,
      "AST": 0,
      "STL": 0,
      "BLK": 0,
      "TOV": 1,
      "PF": 1,
      "PTS": 0,
      "PLUS_MINUS": 5
    },
    {
      "GAME_DATE": "Jan 10, 2025",
      "MATCHUP": "CHI vs. WAS",
      "MIN": 4.0,
      "FGM": 1,
      "FGA": 1,
      "FG3M": 0,
      "FG3A": 0,
      "FTM": 2,
      "FTA": 2,
      "OREB": 0,
      "DREB": 1,
      "REB": 1,
      "AST": 0,
      "STL": 0,
      "BLK": 1,
      "TOV": 0,
      "PF": 0,
      "PTS": 4,
      "PLUS_MINUS": 6
    },
    {
      "GAME_DATE": "Jan 08, 2025",
      "MATCHUP": "CHI @ IND",
      "MIN": 7.0,
      "FGM": 0,
      "FGA": 0,
      "FG3M": 0,
      "FG3A": 0,
      "FTM": 1,
      "FTA": 2,
      "OREB": 0,
      "DREB": 0,
      "REB": 0,
      "AST": 0,
      "STL": 0,
      "BLK": 0,
      "TOV": 0,
      "PF": 0,
      "PTS": 1,
      "PLUS_MINUS": 7
    },
    {
      "GAME_DATE": "Jan 01, 2025",
      "MATCHUP": "CHI @ WAS",
      "MIN": 4.0,
      "FGM": 1,
      "FGA": 1,
      "FG3M": 1,
      "FG3A": 1,
      "FTM": 0,
      "FTA": 0,
      "OREB": 0,
      "DREB": 0,
      "REB": 0,
      "AST": 1,
      "STL": 0,
      "BLK": 0,
      "TOV": 0,
      "PF": 0,
      "PTS": 3,
      "PLUS_MINUS": 0
    },
    {
      "GAME_DATE": "Dec 28, 2024",
      "MATCHUP": "CHI vs. MIL",
      "MIN": 6.0,
      "FGM": 1,
      "FGA": 2,
      "FG3M": 1,
      "FG3A": 2,
      "FTM": 2,
      "FTA": 2,
      "OREB": 0,
      "DREB": 1,
      "REB": 1,
      "AST": 1,
      "STL": 0,
      "BLK": 0,
      "TOV": 0,
      "PF": 0,
      "PTS": 5,
      "PLUS_MINUS": -4
    },
    {
      "GAME_DATE": "Dec 26, 2024",
      "MATCHUP": "CHI @ ATL",
      "MIN": 36.0,
      "FGM": 9,
      "FGA": 15,
      "FG3M": 7,
      "FG3A": 11,
      "FTM": 1,
      "FTA": 2,
      "OREB": 0,
      "DREB": 4,
      "REB": 4,
      "AST": 5,
      "STL": 1,
      "BLK": 0,
      "TOV": 2,
      "PF": 3,
      "PTS": 26,
      "PLUS_MINUS": 7
    },
    {
      "GAME_DATE": "Dec 23, 2024",
      "MATCHUP": "CHI vs. MIL",
      "MIN": 4.0,
      "FGM": 0,
      "FGA": 1,
      "FG3M": 0,
      "FG3A": 1,
      "FTM": 0,
      "FTA": 0,
      "OREB": 0,
      "DREB": 0,
      "REB": 0,
      "AST": 0,
      "STL": 1,
      "BLK": 0,
      "TOV": 0,
      "PF": 0,
      "PTS": 0,
      "PLUS_MINUS": 1
    },
    {
      "GAME_DATE": "Dec 21, 2024",
      "MATCHUP": "CHI vs. BOS",
      "MIN": 4.0,
      "FGM": 2,
      "FGA": 3,
      "FG3M": 0,
      "FG3A": 0,
      "FTM": 0,
      "FTA": 0,
      "OREB": 1,
      "DREB": 0,
      "REB": 1,
      "AST": 1,
      "STL": 0,
      "BLK": 0,
      "TOV": 0,
      "PF": 0,
      "PTS": 4,
      "PLUS_MINUS": 0
    },
    {
      "GAME_DATE": "Dec 05, 2024",
      "MATCHUP": "CHI @ SAS",
      "MIN": 1.0,
      "FGM": 0,
      "FGA": 1,
      "FG3M": 0,
      "FG3A": 1,
      "FTM": 0,
      "FTA": 0,
      "OREB": 0,
      "DREB": 1,
      "REB": 1,
      "AST": 0,
      "STL": 0,
      "BLK": 0,
      "TOV": 0,
      "PF": 0,
      "PTS": 0,
      "PLUS_MINUS": -2
    },
    {
      "GAME_DATE": "Dec 02, 2024",
      "MATCHUP": "CHI vs. BKN",
      "MIN": 4.0,
      "FGM": 0,
      "FGA": 1,
      "FG3M": 0,
      "FG3A": 1,
      "FTM": 0,
      "FTA": 0,
      "OREB": 0,
      "DREB": 1,
      "REB": 1,
      "AST": 0,
      "STL": 0,
      "BLK": 0,
      "TOV": 1,
      "PF": 0,
      "PTS": 0,
      "PLUS_MINUS": 0
    },
    {
      "GAME_DATE": "Nov 27, 2024",
      "MATCHUP": "CHI @ ORL",
      "MIN": 4.0,
      "FGM": 1,
      "FGA": 2,
      "FG3M": 0,
      "FG3A": 1,
      "FTM": 0,
      "FTA": 0,
      "OREB": 0,
      "DREB": 0,
      "REB": 0,
      "AST": 1,
      "STL": 0,
      "BLK": 0,
      "TOV": 0,
      "PF": 0,
      "PTS": 2,
      "PLUS_MINUS": 8
    },
    {
      "GAME_DATE": "Nov 26, 2024",
      "MATCHUP": "CHI @ WAS",
      "MIN": 2.0,
      "FGM": 0,
      "FGA": 0,
      "FG3M": 0,
      "FG3A": 0,
      "FTM": 0,
      "FTA": 0,
      "OREB": 0,
      "DREB": 1,
      "REB": 1,
      "AST": 0,
      "STL": 0,
      "BLK": 0,
      "TOV": 1,
      "PF": 0,
      "PTS": 0,
      "PLUS_MINUS": -5
    },
    {
      "GAME_DATE": "Nov 23, 2024",
      "MATCHUP": "CHI vs. MEM",
      "MIN": 5.0,
      "FGM": 1,
      "FGA": 2,
      "FG3M": 1,
      "FG3A": 2,
      "FTM": 0,
      "FTA": 0,
      "OREB": 0,
      "DREB": 0,
      "REB": 0,
      "AST": 1,
      "STL": 0,
      "BLK": 0,
      "TOV": 1,
      "PF": 0,
      "PTS": 3,
      "PLUS_MINUS": 9
    },
    {
      "GAME_DATE": "Nov 20, 2024",
      "MATCHUP": "CHI @ MIL",
      "MIN": 2.0,
      "FGM": 0,
      "FGA": 2,
      "FG3M": 0,
      "FG3A": 1,
      "FTM": 0,
      "FTA": 0,
      "OREB": 0,
      "DREB": 0,
      "REB": 0,
      "AST": 0,
      "STL": 0,
      "BLK": 0,
      "TOV": 0,
      "PF": 0,
      "PTS": 0,
      "PLUS_MINUS": 0
    },
    {
      "GAME_DATE": "Nov 17, 2024",
      "MATCHUP": "CHI vs. HOU",
      "MIN": 14.0,
      "FGM": 3,
      "FGA": 9,
      "FG3M": 2,
      "FG3A": 6,
      "FTM": 0,
      "FTA": 0,
      "OREB": 0,
      "DREB": 3,
      "REB": 3,
      "AST": 2,
      "STL": 2,
      "BLK": 0,
      "TOV": 1,
      "PF": 1,
      "PTS": 8,
      "PLUS_MINUS": -8
    },
    {
      "GAME_DATE": "Nov 09, 2024",
      "MATCHUP": "CHI @ ATL",
      "MIN": 9.0,
      "FGM": 0,
      "FGA": 3,
      "FG3M": 0,
      "FG3A": 2,
      "FTM": 0,
      "FTA": 0,
      "OREB": 0,
      "DREB": 0,
      "REB": 0,
      "AST": 0,
      "STL": 0,
      "BLK": 0,
      "TOV": 0,
      "PF": 0,
      "PTS": 0,
      "PLUS_MINUS": 10
    },
    {
      "GAME_DATE": "Nov 07, 2024",
      "MATCHUP": "CHI vs. MIN",
      "MIN": 2.0,
      "FGM": 0,
      "FGA": 0,
      "FG3M": 0,
      "FG3A": 0,
      "FTM": 0,
      "FTA": 0,
      "OREB": 0,
      "DREB": 0,
      "REB": 0,
      "AST": 1,
      "STL": 0,
      "BLK": 0,
      "TOV": 0,
      "PF": 0,
      "PTS": 0,
      "PLUS_MINUS": 1
    },
    {
      "GAME_DATE": "Nov 06, 2024",
      "MATCHUP": "CHI @ DAL",
      "MIN": 6.0,
      "FGM": 2,
      "FGA": 2,
      "FG3M": 1,
      "FG3A": 1,
      "FTM": 0,
      "FTA": 0,
      "OREB": 1,
      "DREB": 1,
      "REB": 2,
      "AST": 0,
      "STL": 0,
      "BLK": 0,
      "TOV": 0,
      "PF": 0,
      "PTS": 5,
      "PLUS_MINUS": 6
    },
    {
      "GAME_DATE": "Oct 26, 2024",
      "MATCHUP": "CHI vs. OKC",
      "MIN": 4.0,
      "FGM": 0,
      "FGA": 1,
      "FG3M": 0,
      "FG3A": 1,
      "FTM": 0,
      "FTA": 0,
      "OREB": 0,
      "DREB": 0,
      "REB": 0,
      "AST": 1,
      "STL": 1,
      "BLK": 0,
      "TOV": 0,
      "PF": 0,
      "PTS": 0,
      "PLUS_MINUS": 1
    }
  ]
}