{
  "season_stats": {
    "MIN_avg": 7.4375,
    "MIN_total": 119,
    "FGM_avg": 0.875,
    "FGM_total": 14,
    "FGA_avg": 2.8125,
    "FGA_total": 45,
    "FG3M_avg": 0.25,
    "FG3M_total": 4,
    "FG3A_avg": 1.3125,
    "FG3A_total": 21,
    "FTM_avg": 0.1875,
    "FTM_total": 3,
    "FTA_avg": 0.375,
    "FTA_total": 6,
    "OREB_avg": 0.25,
    "OREB_total": 4,
    "DREB_avg": 0.5625,
    "DREB_total": 9,
    "REB_avg": 0.8125,
    "REB_total": 13,
    "AST_avg": 1.0,
    "AST_total": 16,
    "STL_avg": 0.1875,
    "STL_total": 3,
    "BLK_avg": 0.0,
    "BLK_total": 0,
    "TOV_avg": 0.1875,
    "TOV_total": 3,
    "PF_avg": 0.25,
    "PF_total": 4,
    "PTS_avg": 2.1875,
    "PTS_total": 35,
    "PLUS_MINUS_avg": 0.125,
    "PLUS_MINUS_total": 2,
    "FG_PCT": 0.3111111111111111,
    "FG3_PCT": 0.19047619047619047,
    "FT_PCT": 0.5,
    "games_played": 16
  }
}