{
  "season_stats": {
    "MIN_avg": 6.25,
    "MIN_total": 100,
    "FGM_avg": 1.125,
    "FGM_total": 18,
    "FGA_avg": 1.625,
    "FGA_total": 26,
    "FG3M_avg": 0.1875,
    "FG3M_total": 3,
    "FG3A_avg": 0.4375,
    "FG3A_total": 7,
    "FTM_avg": 0.25,
    "FTM_total": 4,
    "FTA_avg": 0.5625,
    "FTA_total": 9,
    "OREB_avg": 0.375,
    "OREB_total": 6,
    "DREB_avg": 1.375,
    "DREB_total": 22,
    "REB_avg": 1.75,
    "REB_total": 28,
    "AST_avg": 0.25,
    "AST_total": 4,
    "STL_avg": 0.3125,
    "STL_total": 5,
    "BLK_avg": 0.25,
    "BLK_total": 4,
    "TOV_avg": 0.25,
    "TOV_total": 4,
    "PF_avg": 0.6875,
    "PF_total": 11,
    "PTS_avg": 2.6875,
    "PTS_total": 43,
    "PLUS_MINUS_avg": 0.3125,
    "PLUS_MINUS_total": 5,
    "FG_PCT": 0.6923076923076923,
    "FG3_PCT": 0.42857142857142855,
    "FT_PCT": 0.4444444444444444,
    "games_played": 16
  }
}